carbonic/__init__.py
carbonic/py.typed
carbonic/core/__init__.py
carbonic/core/date.py
carbonic/core/datetime.py
carbonic/core/duration.py
carbonic/core/exceptions.py
carbonic/core/interval.py
carbonic/core/period.py
carbonic/core/types.py
carbonic/integrations/__init__.py
carbonic/integrations/pydantic.py
carbonic/locale/__init__.py
carbonic/locale/base.py
carbonic/locale/de.py
carbonic/locale/en.py
carbonic/locale/es.py
carbonic/locale/fr.py
carbonic/locale/pl.py
carbonic/locale/pt.py
carbonic-1.0.2.dist-info/licenses/LICENSE
carbonic-1.0.2.dist-info/METADATA
carbonic-1.0.2.dist-info/WHEEL
carbonic-1.0.2.dist-info/top_level.txt
carbonic-1.0.2.dist-info/RECORD
