Metadata-Version: 2.4
Name: carbonic
Version: 1.0.2
Summary: A modern Python datetime library with fluent API and immutable design
Author-email: Marek Pilczuk <marek@mp76.pl>
Maintainer-email: Marek Pilczuk <marek@mp76.pl>
License-Expression: MIT
Project-URL: Documentation, https://marepilc.github.io/carbonic/
Project-URL: Repository, https://github.com/marepilc/carbonic
Project-URL: Issues, https://github.com/marepilc/carbonic/issues
Project-URL: Changelog, https://github.com/marepilc/carbonic/blob/master/CHANGELOG.md
Keywords: datetime,date,time,fluent,timezone,immutable
Requires-Python: >=3.12
License-File: LICENSE
Requires-Dist: tzdata>=2024.1; platform_system == "Windows"
Provides-Extra: performance
Requires-Dist: ciso8601>=2.3.0; extra == "performance"
Provides-Extra: pydantic
Requires-Dist: pydantic>=2.0.0; extra == "pydantic"
Dynamic: license-file
